loliktry_bangunhitung/__init__.py
loliktry_bangunhitung/rumusnya.py
loliktry_bangunhitung-0.1.4.dist-info/LICENSE
loliktry_bangunhitung-0.1.4.dist-info/METADATA
loliktry_bangunhitung-0.1.4.dist-info/WHEEL
loliktry_bangunhitung-0.1.4.dist-info/top_level.txt
loliktry_bangunhitung-0.1.4.dist-info/RECORD
