Metadata-Version: 2.1
Name: loliktry-bangunhitung
Version: 0.1.4
Summary: Library ini digunakan hanya untuk kesenangan semata tidak untuk sesuatu yang serius.
Home-page: https://github.com/loliktry/pyPi-module
Author: Liliek
Author-email: liliek.triyono@gmail.com
Project-URL: Bug Tracker, https://github.com/loliktry/pyPi-module/issues
Classifier: Programming Language :: Python :: 3
Classifier: License :: OSI Approved :: MIT License
Classifier: Operating System :: OS Independent
Requires-Python: >=3.6
License-File: LICENSE
